[
{"id": "U-3088", "name": "Avans", "formal_name": " Avans Hogeschool 's-Hertogenbosch", "country": "NLD"},
{"id": "U-0635", "name": "TU", "formal_name": " TU Delft ", "country": "NLD"},
{"id": "U-0711", "name": "TU/e", "formal_name": " TU/e ", "country": "NLD"},
{"id": "U-3179", "name": "Katholieke", "formal_name": " Katholieke Universiteit Leuven ", "country": "NLD"},
{"id": "U-1172", "name": "Leiden", "formal_name": " Leiden University ", "country": "NLD"},
{"id": "U-7250", "name": "Radboud", "formal_name": " Radboud University ", "country": "NLD"},
{"id": "U-2097", "name": "Universiteit", "formal_name": " Universiteit van Amsterdam ", "country": "NLD"},
{"id": "U-2307", "name": "University", "formal_name": " University of Twente ", "country": "NLD"},
{"id": "U-3199", "name": "Université", "formal_name": " Université catholique de Louvain ", "country": "NLD"},
{"id": "U-7560", "name": "Université", "formal_name": " Université de Mons ", "country": "NLD"},
{"id": "U-7642", "name": "Université", "formal_name": " Université Libre de Bruxelles ", "country": "NLD"},
{"id": "U-2347", "name": "Utrecht", "formal_name": " Utrecht University ", "country": "NLD"},
{"id": "U-2381", "name": "Vrije", "formal_name": " Vrije Universiteit Amsterdam ", "country": "NLD"},
{"id": "U-10500", "name": "UM", "formal_name": "Universit\u00e4t Maastricht ", "country": "NLD"}
]
